{
    "id": "03612a7e-6460-4ef6-9528-59d60f970b93",
    "address": [
        {
            "city": "Winchester",
            "country": "Middlesex County",
            "postalCode": "nan",
            "state": "Massachusetts",
            "text": "1078 Hauck Station"
        }
    ],
    "birthDate": "1947-03-12",
    "deceasedBoolean": true,
    "deceasedDateTime": "2014-09-18",
    "gender": "M",
    "name": [
        {
            "family": "Marquardt819",
            "given": [
                "Cristobal567"
            ],
            "prefix": [
                "Mr."
            ],
            "suffix": [
                "nan"
            ],
            "text": "Cristobal567 Marquardt819",
            "use": "nan"
        }
    ],
    "resourceType": "Patient"
}