{
    "id": "10ab86b6-a248-4dcf-bebb-3ba143c0ea29",
    "address": [
        {
            "city": "Cambridge",
            "country": "Middlesex County",
            "postalCode": "2472.0",
            "state": "Massachusetts",
            "text": "689 Ankunding Estate"
        }
    ],
    "birthDate": "1982-03-15",
    "deceasedBoolean": false,
    "gender": "M",
    "name": [
        {
            "family": "Connelly992",
            "given": [
                "Blake449"
            ],
            "prefix": [
                "Mr."
            ],
            "suffix": [
                "nan"
            ],
            "text": "Blake449 Connelly992",
            "use": "nan"
        }
    ],
    "resourceType": "Patient"
}