{
    "id": "1a7e8f38-95df-4c27-8897-21ed04c3b98b",
    "address": [
        {
            "city": "Chatham",
            "country": "Barnstable County",
            "postalCode": "2633.0",
            "state": "Massachusetts",
            "text": "380 McGlynn Branch"
        }
    ],
    "birthDate": "1942-05-23",
    "deceasedBoolean": true,
    "deceasedDateTime": "2016-06-10",
    "gender": "M",
    "name": [
        {
            "family": "Cronin387",
            "given": [
                "Lino542"
            ],
            "prefix": [
                "Mr."
            ],
            "suffix": [
                "nan"
            ],
            "text": "Lino542 Cronin387",
            "use": "nan"
        }
    ],
    "resourceType": "Patient"
}