{
    "id": "1c3fea30-6be0-419a-b342-50767fd55440",
    "address": [
        {
            "city": "Worcester",
            "country": "Worcester County",
            "postalCode": "1610.0",
            "state": "Massachusetts",
            "text": "827 Breitenberg Passage"
        }
    ],
    "birthDate": "1984-12-27",
    "deceasedBoolean": false,
    "gender": "F",
    "name": [
        {
            "family": "Llamas954",
            "given": [
                "Adela471"
            ],
            "prefix": [
                "Mrs."
            ],
            "suffix": [
                "nan"
            ],
            "text": "Adela471 Llamas954",
            "use": "Cabrera242"
        }
    ],
    "resourceType": "Patient"
}