{
    "id": "1d996507-b0e3-4ef8-ab62-9db3bd808105",
    "address": [
        {
            "city": "Norwood",
            "country": "Norfolk County",
            "postalCode": "2090.0",
            "state": "Massachusetts",
            "text": "569 Grimes Lane Suite 4"
        }
    ],
    "birthDate": "1914-09-05",
    "deceasedBoolean": true,
    "deceasedDateTime": "1999-09-16",
    "gender": "F",
    "name": [
        {
            "family": "Marvin195",
            "given": [
                "Valentina258"
            ],
            "prefix": [
                "Mrs."
            ],
            "suffix": [
                "nan"
            ],
            "text": "Valentina258 Marvin195",
            "use": "Jerde200"
        }
    ],
    "resourceType": "Patient"
}