{
    "id": "257af8d7-ba2c-4394-9a30-691e6f80d8a6",
    "address": [
        {
            "city": "Barnstable",
            "country": "Barnstable County",
            "postalCode": "2601.0",
            "state": "Massachusetts",
            "text": "117 Hermann Common"
        }
    ],
    "birthDate": "1917-05-31",
    "deceasedBoolean": false,
    "gender": "F",
    "name": [
        {
            "family": "Denesik803",
            "given": [
                "Nickole723"
            ],
            "prefix": [
                "Mrs."
            ],
            "suffix": [
                "nan"
            ],
            "text": "Nickole723 Denesik803",
            "use": "Cruickshank494"
        }
    ],
    "resourceType": "Patient"
}