{
    "id": "25f2b770-8821-48f0-a7fe-460dfe3b15b8",
    "address": [
        {
            "city": "Swansea",
            "country": "Bristol County",
            "postalCode": "nan",
            "state": "Massachusetts",
            "text": "1027 Morar Road"
        }
    ],
    "birthDate": "2000-05-15",
    "deceasedBoolean": false,
    "gender": "M",
    "name": [
        {
            "family": "Hoeger474",
            "given": [
                "Winford225"
            ],
            "prefix": [
                "Mr."
            ],
            "suffix": [
                "nan"
            ],
            "text": "Winford225 Hoeger474",
            "use": "nan"
        }
    ],
    "resourceType": "Patient"
}