{
    "id": "5b5bc31a-0e78-4e08-a183-e2503be440b3",
    "address": [
        {
            "city": "Woburn",
            "country": "Middlesex County",
            "postalCode": "nan",
            "state": "Massachusetts",
            "text": "1071 Brown Ferry"
        }
    ],
    "birthDate": "1961-03-12",
    "deceasedBoolean": false,
    "gender": "M",
    "name": [
        {
            "family": "Sipes176",
            "given": [
                "Chi716"
            ],
            "prefix": [
                "Mr."
            ],
            "suffix": [
                "nan"
            ],
            "text": "Chi716 Sipes176",
            "use": "nan"
        }
    ],
    "resourceType": "Patient"
}