{
    "id": "631107a0-17ac-4d1a-bc95-0089f4ed90f3",
    "address": [
        {
            "city": "Hingham",
            "country": "Plymouth County",
            "postalCode": "2043.0",
            "state": "Massachusetts",
            "text": "586 Weissnat Crossing"
        }
    ],
    "birthDate": "1952-02-29",
    "deceasedBoolean": false,
    "gender": "M",
    "name": [
        {
            "family": "Goodwin327",
            "given": [
                "Erasmo545"
            ],
            "prefix": [
                "Mr."
            ],
            "suffix": [
                "nan"
            ],
            "text": "Erasmo545 Goodwin327",
            "use": "nan"
        }
    ],
    "resourceType": "Patient"
}