{
    "id": "73865a0e-b09d-4604-ad78-f6d2d82f76f8",
    "address": [
        {
            "city": "Marshfield",
            "country": "Plymouth County",
            "postalCode": "nan",
            "state": "Massachusetts",
            "text": "1032 Leannon Bay"
        }
    ],
    "birthDate": "2013-07-22",
    "deceasedBoolean": false,
    "gender": "F",
    "name": [
        {
            "family": "Hagenes547",
            "given": [
                "Aurelia213"
            ],
            "prefix": [
                "nan"
            ],
            "suffix": [
                "nan"
            ],
            "text": "Aurelia213 Hagenes547",
            "use": "nan"
        }
    ],
    "resourceType": "Patient"
}