{
    "id": "9ba75b66-e3a1-4476-9494-586b7a759ea6",
    "address": [
        {
            "city": "Concord",
            "country": "Middlesex County",
            "postalCode": "nan",
            "state": "Massachusetts",
            "text": "926 Nienow Extension Apt 25"
        }
    ],
    "birthDate": "1967-11-27",
    "deceasedBoolean": true,
    "deceasedDateTime": "1995-04-04",
    "gender": "F",
    "name": [
        {
            "family": "Bauch723",
            "given": [
                "Jan231"
            ],
            "prefix": [
                "Mrs."
            ],
            "suffix": [
                "nan"
            ],
            "text": "Jan231 Bauch723",
            "use": "Miller503"
        }
    ],
    "resourceType": "Patient"
}