{
    "id": "bf35e4fa-ea4f-40a4-8fe6-1f2f26e0aa45",
    "address": [
        {
            "city": "Ashland",
            "country": "Middlesex County",
            "postalCode": "nan",
            "state": "Massachusetts",
            "text": "873 Mueller Arcade Unit 96"
        }
    ],
    "birthDate": "2000-11-21",
    "deceasedBoolean": false,
    "gender": "F",
    "name": [
        {
            "family": "Feil794",
            "given": [
                "Cecila397"
            ],
            "prefix": [
                "Ms."
            ],
            "suffix": [
                "nan"
            ],
            "text": "Cecila397 Feil794",
            "use": "nan"
        }
    ],
    "resourceType": "Patient"
}