{
    "id": "dc811097-b472-4dbd-8ce9-bb0afca44d7e",
    "address": [
        {
            "city": "New Bedford",
            "country": "Bristol County",
            "postalCode": "2744.0",
            "state": "Massachusetts",
            "text": "563 Hansen Ranch"
        }
    ],
    "birthDate": "1995-02-18",
    "deceasedBoolean": false,
    "gender": "M",
    "name": [
        {
            "family": "Tillman293",
            "given": [
                "Alan320"
            ],
            "prefix": [
                "Mr."
            ],
            "suffix": [
                "nan"
            ],
            "text": "Alan320 Tillman293",
            "use": "nan"
        }
    ],
    "resourceType": "Patient"
}