{
    "id": "ed043572-d676-4b8b-86d0-435151812fd4",
    "address": [
        {
            "city": "Ashburnham",
            "country": "Worcester County",
            "postalCode": "nan",
            "state": "Massachusetts",
            "text": "701 Hartmann Drive"
        }
    ],
    "birthDate": "1994-10-09",
    "deceasedBoolean": false,
    "gender": "F",
    "name": [
        {
            "family": "Medhurst46",
            "given": [
                "Gracie337"
            ],
            "prefix": [
                "Ms."
            ],
            "suffix": [
                "nan"
            ],
            "text": "Gracie337 Medhurst46",
            "use": "nan"
        }
    ],
    "resourceType": "Patient"
}