{
    "id": "f54dd1af-4b23-4781-9c2e-1960bdccac29",
    "address": [
        {
            "city": "Worcester",
            "country": "Worcester County",
            "postalCode": "1602.0",
            "state": "Massachusetts",
            "text": "1095 Sauer Route"
        }
    ],
    "birthDate": "1977-10-15",
    "deceasedBoolean": false,
    "gender": "F",
    "name": [
        {
            "family": "Lind531",
            "given": [
                "Esmeralda972"
            ],
            "prefix": [
                "Ms."
            ],
            "suffix": [
                "nan"
            ],
            "text": "Esmeralda972 Lind531",
            "use": "nan"
        }
    ],
    "resourceType": "Patient"
}