{
    "id": "fcc61454-1b07-4e49-a25b-29e5064e0063",
    "address": [
        {
            "city": "Marlborough",
            "country": "Middlesex County",
            "postalCode": "1752.0",
            "state": "Massachusetts",
            "text": "341 Homenick Trailer Suite 77"
        }
    ],
    "birthDate": "1966-07-06",
    "deceasedBoolean": false,
    "gender": "M",
    "name": [
        {
            "family": "Farrell962",
            "given": [
                "Patrick786"
            ],
            "prefix": [
                "Mr."
            ],
            "suffix": [
                "nan"
            ],
            "text": "Patrick786 Farrell962",
            "use": "nan"
        }
    ],
    "resourceType": "Patient"
}